CHANGES
LICENSE
MANIFEST.in
README.rst
setup.cfg
setup.py
tox.ini
docs/Makefile
docs/api.rst
docs/conf.py
docs/contributing.rst
docs/index.rst
docs/quickstart.rst
docs/_static/empty
pyramid_es/__init__.py
pyramid_es/client.py
pyramid_es/dotdict.py
pyramid_es/mixin.py
pyramid_es/query.py
pyramid_es/result.py
pyramid_es.egg-info/PKG-INFO
pyramid_es.egg-info/SOURCES.txt
pyramid_es.egg-info/dependency_links.txt
pyramid_es.egg-info/not-zip-safe
pyramid_es.egg-info/requires.txt
pyramid_es.egg-info/top_level.txt
pyramid_es/tests/__init__.py
pyramid_es/tests/data.py
pyramid_es/tests/test_dotdict.py
pyramid_es/tests/test_functional.py
pyramid_es/tests/test_mixin.py
pyramid_es/tests/test_pyramid.py
pyramid_es/tests/test_result.py
pyramid_es/tests/test_transaction.py