Metadata-Version: 1.1
Name: pyramid-es
Version: 0.3.1
Summary: Elasticsearch integration for Pyramid.
Home-page: http://github.com/cartlogic/pyramid_es
Author: Scott Torborg
Author-email: scott@cartlogic.com
License: MIT
Keywords: pyramid search elasticsearch
Platform: UNKNOWN
Classifier: Development Status :: 2 - Pre-Alpha
Classifier: License :: OSI Approved :: MIT License
Classifier: Programming Language :: Python :: 2
Classifier: Programming Language :: Python :: 2.7
Classifier: Programming Language :: Python :: 3
Classifier: Programming Language :: Python :: 3.3
Classifier: Programming Language :: Python :: 3.4
Classifier: Framework :: Pyramid
Classifier: Topic :: Internet :: WWW/HTTP :: Indexing/Search
